{
  "project_info": {
    "project_number": "216982144122",
    "project_id": "auth-ed5cb",
    "storage_bucket": "auth-ed5cb.appspot.com"
  },
  "client": [
    {
      "client_info": {
        "mobilesdk_app_id": "1:216982144122:android:8e700f2c7f5afa3987a7c3",
        "android_client_info": {
          "package_name": "com.example.week9_authentication"
        }
      },
      "oauth_client": [],
      "api_key": [
        {
          "current_key": "AIzaSyDi683zGYc7Gg43dOq9LGXdcR5AcEhraAw"
        }
      ],
      "services": {
        "appinvite_service": {
          "other_platform_oauth_client": []
        }
      }
    }
  ],
  "configuration_version": "1"
}